poetry/__main__.py
poetry/__version__.py
poetry/config/__init__.py
poetry/config/config.py
poetry/config/config_source.py
poetry/config/dict_config_source.py
poetry/config/file_config_source.py
poetry/config/source.py
poetry/console/__init__.py
poetry/console/application.py
poetry/console/command_loader.py
poetry/console/commands/__init__.py
poetry/console/commands/about.py
poetry/console/commands/add.py
poetry/console/commands/build.py
poetry/console/commands/cache/__init__.py
poetry/console/commands/cache/clear.py
poetry/console/commands/cache/list.py
poetry/console/commands/check.py
poetry/console/commands/command.py
poetry/console/commands/config.py
poetry/console/commands/debug/__init__.py
poetry/console/commands/debug/info.py
poetry/console/commands/debug/resolve.py
poetry/console/commands/env/__init__.py
poetry/console/commands/env/info.py
poetry/console/commands/env/list.py
poetry/console/commands/env/remove.py
poetry/console/commands/env/use.py
poetry/console/commands/env_command.py
poetry/console/commands/group_command.py
poetry/console/commands/init.py
poetry/console/commands/install.py
poetry/console/commands/installer_command.py
poetry/console/commands/lock.py
poetry/console/commands/new.py
poetry/console/commands/publish.py
poetry/console/commands/remove.py
poetry/console/commands/run.py
poetry/console/commands/search.py
poetry/console/commands/self/__init__.py
poetry/console/commands/self/add.py
poetry/console/commands/self/install.py
poetry/console/commands/self/lock.py
poetry/console/commands/self/remove.py
poetry/console/commands/self/self_command.py
poetry/console/commands/self/show/__init__.py
poetry/console/commands/self/show/plugins.py
poetry/console/commands/self/update.py
poetry/console/commands/shell.py
poetry/console/commands/show.py
poetry/console/commands/source/__init__.py
poetry/console/commands/source/add.py
poetry/console/commands/source/remove.py
poetry/console/commands/source/show.py
poetry/console/commands/update.py
poetry-1.6.0.dist-info/LICENSE
poetry-1.6.0.dist-info/METADATA
poetry-1.6.0.dist-info/WHEEL
poetry-1.6.0.dist-info/entry_points.txt
poetry-1.6.0.dist-info/RECORD
