Metadata-Version: 2.1
Name: poetry
Version: 1.6.0
Summary: Python dependency management and packaging made easy.
Home-page: https://python-poetry.org/
License: MIT
Keywords: packaging,dependency,poetry
Author: Sébastien Eustace
Author-email: sebastien@eustace.io
Maintainer: Arun Babu Neelicattu
Maintainer-email: arun.neelicattu@gmail.com
Requires-Python: >=3.8,<4.0
Classifier: License :: OSI Approved :: MIT License
Classifier: Programming Language :: Python :: 3
Classifier: Programming Language :: Python :: 3.8
Classifier: Programming Language :: Python :: 3.9
Classifier: Programming Language :: Python :: 3.10
Classifier: Programming Language :: Python :: 3.11
Classifier: Topic :: Software Development :: Build Tools
Classifier: Topic :: Software Development :: Libraries :: Python Modules
Requires-Dist: build (>=0.10.0,<0.11.0)
Requires-Dist: cachecontrol[filecache] (>=0.13.0,<0.14.0)
Requires-Dist: cleo (>=2.0.0,<3.0.0)
Requires-Dist: crashtest (>=0.4.1,<0.5.0)
Requires-Dist: dulwich (>=0.21.2,<0.22.0)
Requires-Dist: importlib-metadata (>=4.4) ; python_version < "3.10"
Requires-Dist: installer (>=0.7.0,<0.8.0)
Requires-Dist: jsonschema (>=4.10.0,<4.18.0)
Requires-Dist: keyring (>=24.0.0,<25.0.0)
Requires-Dist: packaging (>=20.4)
Requires-Dist: pexpect (>=4.7.0,<5.0.0)
Requires-Dist: pkginfo (>=1.9.4,<2.0.0)
Requires-Dist: platformdirs (>=3.0.0,<4.0.0)
Requires-Dist: poetry-core (==1.7.0)
Requires-Dist: poetry-plugin-export (>=1.5.0,<2.0.0)
Requires-Dist: pyproject-hooks (>=1.0.0,<2.0.0)
Requires-Dist: requests (>=2.18,<3.0)
Requires-Dist: requests-toolbelt (>=0.9.1,<2)
Requires-Dist: shellingham (>=1.5,<2.0)
Requires-Dist: tomli (>=2.0.1,<3.0.0) ; python_version < "3.11"
Requires-Dist: tomlkit (>=0.11.4,<1.0.0)
Requires-Dist: trove-classifiers (>=2022.5.19)
Requires-Dist: virtualenv (>=20.22.0,<21.0.0)
Requires-Dist: xattr (>=0.10.0,<0.11.0) ; sys_platform == "darwin"
Project-URL: Changelog, https://python-poetry.org/history/
Project-URL: Documentation, https://python-poetry.org/docs
Project-URL: Repository, https://github.com/python-poetry/poetry
